Workbook
Name aport: Planilha1!$D$14:$D$14
Name aporte: Planilha1!$D$14:$D$14
Name patrimonio: Planilha1!$D$17:$D$17
Name qtd_anos: Planilha1!$D$15:$D$15
Name rendimento_carteira: Planilha1!$D$10:$D$10
Name salario: Planilha1!$D$9:$D$9
Name sugestao_investimento: Planilha1!$D$11:$D$11
Name taxa_mensal: Planilha1!$D$16:$D$16

Sheet Planilha1
B8: Pré-configurações
B9: Seu salário: | D9: 2000 | E9: Informe seu salário
B10: Rendimento da carteira: | D10: 0.0089 | E10: Informe o rendimento da carteira
B11: Sugestão de investimento: | D11: =D9*30% -> 600
B13: INVESTIMENTO MENSAL
B14: Quanto você consegue investir todo mês? | D14: 400 | E14: Informe quanto pretende investir
B15: Por quanto tempo você pretende investir? | D15: 5 | E15: Informe quantos anos quer investr
B16: Taxa de rendimento mensal? | D16: 0.01079
B17: Patrimônio acumulado ao final do período: | D17: {=FV(taxa_mensal,qtd_anos*12,aporte*-1)} -> 33510.766
B18: Quanto o patrimônio pode gerar por mês: | D18: {=patrimonio*rendimento_carteira} -> 298.24581
B20: PROJEÇÃO DE LONGO PRAZO | D20: DIVIDENDOS
A21: 2 | B21: Prazo de 2 anos | C21: =FV($D$16,$A21*12,$D$14*-1) -> 10891.051 | D21: {=C21*rendimento_carteira} -> 96.930353
A22: 5 | B22: Prazo de 5 anos | C22: =FV($D$16,$A22*12,$D$14*-1) -> 33510.766 | D22: {=C22*rendimento_carteira} -> 298.24581
A23: 10 | B23: Prazo de 10 anos | C23: =FV($D$16,$A23*12,$D$14*-1) -> 97313.685 | D23: {=C23*rendimento_carteira} -> 866.0918
A24: 20 | B24: Prazo de 20 anos | C24: =FV($D$16,$A24*12,$D$14*-1) -> 450079.36 | D24: {=C24*rendimento_carteira} -> 4005.7063
A25: 30 | B25: Prazo de 30 anos | C25: =FV($D$16,$A25*12,$D$14*-1) -> 1728867.9 | D25: {=C25*rendimento_carteira} -> 15386.924
B28: PERFIL DO INVESTIDOR | C28: Agressivo | E28: Selecione seu perfil
B29: Valor a ser investido por mês: | C29: {=aporte} -> 400
B31: TIPO DE FII | C31: Percentual sugerido | D31: Valores
B32: Papel | C32: =VLOOKUP($C$28&"-"&B32,Tabela_Perfil!$A:$D,4,FALSE) -> 0.5 | D32: =C32*$C$29 -> 200
B33: Tijolo | C33: =VLOOKUP($C$28&"-"&B33,Tabela_Perfil!$A:$D,4,FALSE) -> 0.1 | D33: =C33*$C$29 -> 40
B34: Híbridos | C34: =VLOOKUP($C$28&"-"&B34,Tabela_Perfil!$A:$D,4,FALSE) -> 0.05 | D34: =C34*$C$29 -> 20
B35: FOFs | C35: =VLOOKUP($C$28&"-"&B35,Tabela_Perfil!$A:$D,4,FALSE) -> 0.05 | D35: =C35*$C$29 -> 20
B36: Desenvolvimento | C36: =VLOOKUP($C$28&"-"&B36,Tabela_Perfil!$A:$D,4,FALSE) -> 0.2 | D36: =C36*$C$29 -> 80
B37: Hotelarias | C37: =VLOOKUP($C$28&"-"&B37,Tabela_Perfil!$A:$D,4,FALSE) -> 0.1 | D37: =C37*$C$29 -> 40
D38: =SUM(D32:D37) -> 400

Sheet Tabela_Perfil
A2: CHAVE | B2: PERFIL | C2: TIPO DE FII | D2: PERCENTUAL
A3: =B3&"-"&C3 -> Conservador-Papel | B3: Conservador | C3: Papel | D3: 0.3
A4: =B4&"-"&C4 -> Conservador-Tijolo | B4: Conservador | C4: Tijolo | D4: 0.5 | G4: CHAVE | H4: %
A5: =B5&"-"&C5 -> Conservador-Híbridos | B5: Conservador | C5: Híbridos | D5: 0.1 | G5: Moderado-Tijolo | H5: =VLOOKUP(G5,$A:$D,4,FALSE) -> 0.35
A6: =B6&"-"&C6 -> Conservador-FOFs | B6: Conservador | C6: FOFs | D6: 0.1
A7: =B7&"-"&C7 -> Conservador-Desenvolvimento | B7: Conservador | C7: Desenvolvimento | D7: 0
A8: =B8&"-"&C8 -> Conservador-Hotelarias | B8: Conservador | C8: Hotelarias | D8: 0
A9: =B9&"-"&C9 -> Moderado-Papel | B9: Moderado | C9: Papel | D9: 0.32
A10: =B10&"-"&C10 -> Moderado-Tijolo | B10: Moderado | C10: Tijolo | D10: 0.35
A11: =B11&"-"&C11 -> Moderado-Híbridos | B11: Moderado | C11: Híbridos | D11: 0.08
A12: =B12&"-"&C12 -> Moderado-FOFs | B12: Moderado | C12: FOFs | D12: 0.05
A13: =B13&"-"&C13 -> Moderado-Desenvolvimento | B13: Moderado | C13: Desenvolvimento | D13: 0.1
A14: =B14&"-"&C14 -> Moderado-Hotelarias | B14: Moderado | C14: Hotelarias | D14: 0.1
A15: =B15&"-"&C15 -> Agressivo-Papel | B15: Agressivo | C15: Papel | D15: 0.5
A16: =B16&"-"&C16 -> Agressivo-Tijolo | B16: Agressivo | C16: Tijolo | D16: 0.1
A17: =B17&"-"&C17 -> Agressivo-Híbridos | B17: Agressivo | C17: Híbridos | D17: 0.05
... A20: =B20&"-"&C20 -> Agressivo-Hotelarias | B20: Agressivo | C20: Hotelarias | D20: 0.1
